grid/__init__.py
grid/__main__.py
grid/benchmark.py
grid/dir.py
grid/gagent.py
grid/gimage.py
grid/gmap.py
grid/grid.py
grid/gridGUI.py
grid/gtest.py
grid/guser.py
grid/io.py
grid/lib.py
grid/demo/seg_img.jpg
grid/gui/__init__.py
grid/gui/anchor.py
grid/gui/cropper.py
grid/gui/customQt.py
grid/gui/inputer.py
grid/gui/kmeaner.py
grid/gui/outputer.py
grid/res/rotate.png
photo_grid-1.3.13.dist-info/LICENSE
photo_grid-1.3.13.dist-info/METADATA
photo_grid-1.3.13.dist-info/WHEEL
photo_grid-1.3.13.dist-info/entry_points.txt
photo_grid-1.3.13.dist-info/top_level.txt
photo_grid-1.3.13.dist-info/RECORD
