Metadata-Version: 2.1
Name: photo_grid
Version: 1.3.13
Summary: A GUI for field segmentation
Home-page: https://github.com/Poissonfish/GRID
Author: James Chen
Author-email: niche@vt.edu
License: GPLv3
Classifier: Programming Language :: Python :: 3.6
Classifier: Programming Language :: Python :: 3.7
Classifier: Programming Language :: Python :: 3.8
Classifier: Programming Language :: Python :: 3.9
Classifier: Programming Language :: Python :: 3.10
Classifier: Programming Language :: Python :: 3.11
Classifier: License :: OSI Approved :: GNU General Public License v3 (GPLv3)
Classifier: Operating System :: MacOS :: MacOS X
Classifier: Operating System :: Microsoft :: Windows :: Windows 10
Requires-Python: >=3.6
License-File: LICENSE
Requires-Dist: numpy
Requires-Dist: pandas>=0.19.2
Requires-Dist: h5py
Requires-Dist: pyshp
Requires-Dist: scikit-learn
Requires-Dist: scipy
Requires-Dist: matplotlib
Requires-Dist: image
Requires-Dist: opencv-python
Requires-Dist: rasterio
Requires-Dist: PyQt6
Requires-Dist: qdarkstyle
Requires-Dist: tqdm
